{"placements":[{"x":650,"y":413},{"x":660,"y":413},{"x":670,"y":413},{"x":680,"y":413},{"x":690,"y":413},{"x":700,"y":413},{"x":710,"y":413},{"x":720,"y":413},{"x":730,"y":413},{"x":740,"y":413},{"x":750,"y":413},{"x":760,"y":413},{"x":770,"y":413},{"x":780,"y":413},{"x":650,"y":423},{"x":660,"y":423},{"x":670,"y":423},{"x":680,"y":423},{"x":690,"y":423},{"x":700,"y":423},{"x":710,"y":423},{"x":720,"y":423},{"x":730,"y":423},{"x":740,"y":423},{"x":750,"y":423},{"x":760,"y":423},{"x":770,"y":423},{"x":780,"y":423},{"x":650,"y":433},{"x":660,"y":433},{"x":670,"y":433},{"x":680,"y":433},{"x":690,"y":433},{"x":700,"y":433}]}